st_selectable_grid/__init__.py
st_selectable_grid/example.py
st_selectable_grid/frontend/build/asset-manifest.json
st_selectable_grid/frontend/build/bootstrap.min.css
st_selectable_grid/frontend/build/index.html
st_selectable_grid/frontend/build/static/css/main.c328cc83.css
st_selectable_grid/frontend/build/static/css/main.c328cc83.css.map
st_selectable_grid/frontend/build/static/js/main.2bfd3e26.js
st_selectable_grid/frontend/build/static/js/main.2bfd3e26.js.LICENSE.txt
st_selectable_grid/frontend/build/static/js/main.2bfd3e26.js.map
st_selectable_grid-1.0.0.dist-info/licenses/LICENSE
st_selectable_grid-1.0.0.dist-info/METADATA
st_selectable_grid-1.0.0.dist-info/WHEEL
st_selectable_grid-1.0.0.dist-info/top_level.txt
st_selectable_grid-1.0.0.dist-info/RECORD
